{
  "variables": [
    {
      "name": "$animation-slide-up",
      "value": "slide-up 0.3s",
      "compiledValue": "slide-up 0.3s"
    },
    {
      "name": "$animation-slide-up-with-margin",
      "value": "slide-up-with-margin 0.3s",
      "compiledValue": "slide-up-with-margin 0.3s"
    },
    {
      "name": "$animation-spinner",
      "value": "rotate 1.2s infinite cubic-bezier(0.55, 0, 0.1, 1)",
      "compiledValue": "rotate 1.2s infinite cubic-bezier(0.55, 0, 0.1, 1)"
    },
    {
      "name": "$animation-glow",
      "value": "glow 1.5s ease-in-out infinite",
      "compiledValue": "glow 1.5s ease-in-out infinite"
    },
    {
      "name": "$radius-xl",
      "value": "10px",
      "compiledValue": "10px"
    },
    {
      "name": "$radius-l",
      "value": "8px",
      "compiledValue": "8px"
    },
    {
      "name": "$radius-m",
      "value": "4px",
      "compiledValue": "4px"
    },
    {
      "name": "$radius-s",
      "value": "2px",
      "compiledValue": "2px"
    },
    {
      "name": "$radius-circle",
      "value": "50%",
      "compiledValue": "50%"
    },
    {
      "name": "$shadow-s",
      "value": "0 0 0 1px rgba(92, 106, 196, 0.1)",
      "compiledValue": "0 0 0 1px rgba(92, 106, 196, 0.1)"
    },
    {
      "name": "$shadow-m",
      "value": "0 3px 6px rgba(0, 0, 0, 0.16)",
      "compiledValue": "0 3px 6px rgba(0, 0, 0, 0.16)"
    },
    {
      "name": "$shadow-l",
      "value": "0 3px 12px rgba(0, 0, 0, 0.33)",
      "compiledValue": "0 3px 12px rgba(0, 0, 0, 0.33)"
    },
    {
      "name": "$color-white",
      "value": "rgb(255, 255, 255)",
      "compiledValue": "white"
    },
    {
      "name": "$color-gray",
      "value": "rgb(145, 145, 145)",
      "compiledValue": "#919191"
    },
    {
      "name": "$color-black",
      "value": "rgb(33, 33, 33)",
      "compiledValue": "#212121"
    },
    {
      "name": "$color-blue",
      "value": "rgb(62, 132, 244)",
      "compiledValue": "#3e84f4"
    },
    {
      "name": "$color-green",
      "value": "rgb(113, 193, 116)",
      "compiledValue": "#71c174"
    },
    {
      "name": "$color-orange",
      "value": "rgb(250, 175, 0)",
      "compiledValue": "#faaf00"
    },
    {
      "name": "$color-red",
      "value": "rgb(244, 62, 62)",
      "compiledValue": "#f43e3e"
    },
    {
      "name": "$duration-s",
      "value": "150ms",
      "compiledValue": "150ms"
    },
    {
      "name": "$duration-m",
      "value": "300ms",
      "compiledValue": "300ms"
    },
    {
      "name": "$duration-l",
      "value": "500ms",
      "compiledValue": "500ms"
    },
    {
      "name": "$easing-swift",
      "value": "cubic-bezier(0.55, 0, 0.1, 1)",
      "compiledValue": "cubic-bezier(0.55, 0, 0.1, 1)"
    },
    {
      "name": "$font-family-heading",
      "value": "'Montserrat', sans-serif",
      "compiledValue": "Montserrat, sans-serif"
    },
    {
      "name": "$font-family-additional",
      "value": "'Source Serif Pro', serif",
      "compiledValue": "Source Serif Pro, serif"
    },
    {
      "name": "$font-size-xxs",
      "value": "8px",
      "compiledValue": "8px"
    },
    {
      "name": "$font-size-xs",
      "value": "10px",
      "compiledValue": "10px"
    },
    {
      "name": "$font-size-s",
      "value": "13px",
      "compiledValue": "13px"
    },
    {
      "name": "$font-size-m",
      "value": "16px",
      "compiledValue": "16px"
    },
    {
      "name": "$font-size-l",
      "value": "20px",
      "compiledValue": "20px"
    },
    {
      "name": "$font-size-xl",
      "value": "28px",
      "compiledValue": "28px"
    },
    {
      "name": "$font-size-xxl",
      "value": "34px",
      "compiledValue": "34px"
    },
    {
      "name": "$font-size-3xl",
      "value": "48px",
      "compiledValue": "48px"
    },
    {
      "name": "$font-size-4xl",
      "value": "56px",
      "compiledValue": "56px"
    },
    {
      "name": "$font-size-5xl",
      "value": "64px",
      "compiledValue": "64px"
    },
    {
      "name": "$font-weight-light",
      "value": "300",
      "compiledValue": "300"
    },
    {
      "name": "$font-weight-regular",
      "value": "400",
      "compiledValue": "400"
    },
    {
      "name": "$font-weight-medium",
      "value": "500",
      "compiledValue": "500"
    },
    {
      "name": "$font-weight-semi-bold",
      "value": "600",
      "compiledValue": "600"
    },
    {
      "name": "$font-weight-bold",
      "value": "700",
      "compiledValue": "700"
    },
    {
      "name": "$gradient-primary-radial",
      "value": "radial-gradient(rgb(179, 211, 255), rgb(62, 132, 244))",
      "compiledValue": "radial-gradient(#b3d3ff, #3e84f4)"
    },
    {
      "name": "$gradient-auth",
      "value": "linear-gradient(-42deg, rgb(57, 28, 95), rgb(91, 39, 112))",
      "compiledValue": "linear-gradient(-42deg, #391c5f, #5b2770)"
    },
    {
      "name": "$letter-spacing-m",
      "value": "0.4px",
      "compiledValue": "0.4px"
    },
    {
      "name": "$letter-spacing-l",
      "value": "1px",
      "compiledValue": "1px"
    },
    {
      "name": "$line-height-xs",
      "value": "1",
      "compiledValue": "1"
    },
    {
      "name": "$line-height-s",
      "value": "1.3",
      "compiledValue": "1.3"
    },
    {
      "name": "$line-height-m",
      "value": "1.6",
      "compiledValue": "1.6"
    },
    {
      "name": "$media-query-xs",
      "value": "(min-width: 375px)",
      "mapValue": [
        {
          "name": "min-width",
          "value": "375px",
          "compiledValue": "375px"
        }
      ],
      "compiledValue": "(min-width: 375px)"
    },
    {
      "name": "$media-query-s",
      "value": "(min-width: 480px)",
      "mapValue": [
        {
          "name": "min-width",
          "value": "480px",
          "compiledValue": "480px"
        }
      ],
      "compiledValue": "(min-width: 480px)"
    },
    {
      "name": "$media-query-m",
      "value": "(min-width: 768px)",
      "mapValue": [
        {
          "name": "min-width",
          "value": "768px",
          "compiledValue": "768px"
        }
      ],
      "compiledValue": "(min-width: 768px)"
    },
    {
      "name": "$media-query-l",
      "value": "(min-width: 1024px)",
      "mapValue": [
        {
          "name": "min-width",
          "value": "1024px",
          "compiledValue": "1024px"
        }
      ],
      "compiledValue": "(min-width: 1024px)"
    },
    {
      "name": "$media-query-xl",
      "value": "(min-width: 1200px)",
      "mapValue": [
        {
          "name": "min-width",
          "value": "1200px",
          "compiledValue": "1200px"
        }
      ],
      "compiledValue": "(min-width: 1200px)"
    },
    {
      "name": "$media-query-xxl",
      "value": "(min-width: 1440px)",
      "mapValue": [
        {
          "name": "min-width",
          "value": "1440px",
          "compiledValue": "1440px"
        }
      ],
      "compiledValue": "(min-width: 1440px)"
    },
    {
      "name": "$media-query-xs-down",
      "value": "(max-width: 374px)",
      "mapValue": [
        {
          "name": "max-width",
          "value": "374px",
          "compiledValue": "374px"
        }
      ],
      "compiledValue": "(max-width: 374px)"
    },
    {
      "name": "$media-query-s-down",
      "value": "(max-width: 479px)",
      "mapValue": [
        {
          "name": "max-width",
          "value": "479px",
          "compiledValue": "479px"
        }
      ],
      "compiledValue": "(max-width: 479px)"
    },
    {
      "name": "$media-query-m-down",
      "value": "(max-width: 767px)",
      "mapValue": [
        {
          "name": "max-width",
          "value": "767px",
          "compiledValue": "767px"
        }
      ],
      "compiledValue": "(max-width: 767px)"
    },
    {
      "name": "$media-query-l-down",
      "value": "(max-width: 1023px)",
      "mapValue": [
        {
          "name": "max-width",
          "value": "1023px",
          "compiledValue": "1023px"
        }
      ],
      "compiledValue": "(max-width: 1023px)"
    },
    {
      "name": "$media-query-xl-down",
      "value": "(max-width: 1199px)",
      "mapValue": [
        {
          "name": "max-width",
          "value": "1199px",
          "compiledValue": "1199px"
        }
      ],
      "compiledValue": "(max-width: 1199px)"
    },
    {
      "name": "$media-query-xxl-down",
      "value": "(max-width: 1439px)",
      "mapValue": [
        {
          "name": "max-width",
          "value": "1439px",
          "compiledValue": "1439px"
        }
      ],
      "compiledValue": "(max-width: 1439px)"
    },
    {
      "name": "$opacity-disabled",
      "value": "0.6",
      "compiledValue": "0.6"
    },
    {
      "name": "$opacity-active",
      "value": "0.7",
      "compiledValue": "0.7"
    },
    {
      "name": "$opacity-hover",
      "value": "0.8",
      "compiledValue": "0.8"
    },
    {
      "name": "$height-footer",
      "value": "64px",
      "compiledValue": "64px"
    },
    {
      "name": "$height-header",
      "value": "65px",
      "compiledValue": "65px"
    },
    {
      "name": "$height-top-line",
      "value": "56px",
      "compiledValue": "56px"
    },
    {
      "name": "$height-table-head",
      "value": "48px",
      "compiledValue": "48px"
    },
    {
      "name": "$height-auth",
      "value": "665px",
      "compiledValue": "665px"
    },
    {
      "name": "$tappable-element-xl",
      "value": "72px",
      "compiledValue": "72px"
    },
    {
      "name": "$tappable-element-l",
      "value": "48px",
      "compiledValue": "48px"
    },
    {
      "name": "$tappable-element-m",
      "value": "40px",
      "compiledValue": "40px"
    },
    {
      "name": "$tappable-element-s",
      "value": "32px",
      "compiledValue": "32px"
    },
    {
      "name": "$tappable-element-xs",
      "value": "24px",
      "compiledValue": "24px"
    },
    {
      "name": "$tappable-element-xxs",
      "value": "16px",
      "compiledValue": "16px"
    },
    {
      "name": "$tappable-element-3xs",
      "value": "12px",
      "compiledValue": "12px"
    },
    {
      "name": "$avatar-xs",
      "value": "24px",
      "compiledValue": "24px"
    },
    {
      "name": "$avatar-s",
      "value": "32px",
      "compiledValue": "32px"
    },
    {
      "name": "$avatar-m",
      "value": "42px",
      "compiledValue": "42px"
    },
    {
      "name": "$avatar-l",
      "value": "56px",
      "compiledValue": "56px"
    },
    {
      "name": "$avatar-xl",
      "value": "92px",
      "compiledValue": "92px"
    },
    {
      "name": "$separator-s",
      "value": "2px",
      "compiledValue": "2px"
    },
    {
      "name": "$separator-xs",
      "value": "1px",
      "compiledValue": "1px"
    },
    {
      "name": "$panel-xl",
      "value": "500px",
      "compiledValue": "500px"
    },
    {
      "name": "$panel-l",
      "value": "380px",
      "compiledValue": "380px"
    },
    {
      "name": "$panel-m",
      "value": "320px",
      "compiledValue": "320px"
    },
    {
      "name": "$panel-s",
      "value": "250px",
      "compiledValue": "250px"
    },
    {
      "name": "$container-m",
      "value": "1064px",
      "compiledValue": "1064px"
    },
    {
      "name": "$container-s",
      "value": "810px",
      "compiledValue": "810px"
    },
    {
      "name": "$site-width-m",
      "value": "1200px",
      "compiledValue": "1200px"
    },
    {
      "name": "$space-3s",
      "value": "2px",
      "compiledValue": "2px"
    },
    {
      "name": "$space-xxs",
      "value": "4px",
      "compiledValue": "4px"
    },
    {
      "name": "$space-xs",
      "value": "8px",
      "compiledValue": "8px"
    },
    {
      "name": "$space-s",
      "value": "12px",
      "compiledValue": "12px"
    },
    {
      "name": "$space-m",
      "value": "16px",
      "compiledValue": "16px"
    },
    {
      "name": "$space-l",
      "value": "20px",
      "compiledValue": "20px"
    },
    {
      "name": "$space-xl",
      "value": "24px",
      "compiledValue": "24px"
    },
    {
      "name": "$space-xxl",
      "value": "32px",
      "compiledValue": "32px"
    },
    {
      "name": "$space-3xl",
      "value": "48px",
      "compiledValue": "48px"
    },
    {
      "name": "$space-4xl",
      "value": "64px",
      "compiledValue": "64px"
    },
    {
      "name": "$space-5xl",
      "value": "128px",
      "compiledValue": "128px"
    },
    {
      "name": "$z-index-dropdown",
      "value": "100",
      "compiledValue": "100"
    },
    {
      "name": "$z-index-sticky",
      "value": "100",
      "compiledValue": "100"
    },
    {
      "name": "$z-index-modal",
      "value": "9999",
      "compiledValue": "9999"
    },
    {
      "name": "$z-index-top-line",
      "value": "9999",
      "compiledValue": "9999"
    },
    {
      "name": "$z-index-header",
      "value": "10000",
      "compiledValue": "10000"
    },
    {
      "name": "$z-index-notification",
      "value": "10001",
      "compiledValue": "10001"
    },
    {
      "name": "$z-index-overlay",
      "value": "10002",
      "compiledValue": "10002"
    }
  ]
}